levy_package/__init__.py
levy_package/__main__.py
levy_package/my_module.py
levy_package/subpackage/__init__.py
levy_package/subpackage/goodbye.py
levy_package/subpackage/hello.py
levy_package-0.1.0.dist-info/METADATA
levy_package-0.1.0.dist-info/WHEEL
levy_package-0.1.0.dist-info/entry_points.txt
levy_package-0.1.0.dist-info/RECORD
