Metadata-Version: 2.3
Name: levy-package
Version: 0.1.0
Summary: Add your description here
Requires-Python: >=3.12
Requires-Dist: numpy>=2.1.3
Requires-Dist: pandas>=2.2.3
Provides-Extra: excel
Requires-Dist: openpyxl>=3.1.5; extra == 'excel'
